<?xml version="1.0" encoding="utf-8" ?><dwsync><file name="options-permalink.php" server="ftp.jackasstheology.com" local="3591803506" remote="3631730220" Dst="-1" /><file name="post-new.php" server="ftp.jackasstheology.com" local="3623237200" remote="3631730220" Dst="-1" /><file name="update.php" server="ftp.jackasstheology.com" local="3590438688" remote="3631730220" Dst="-1" /><file name="revision.php" server="ftp.jackasstheology.com" local="3562564952" remote="3631730220" Dst="-1" /><file name="widgets.php" server="ftp.jackasstheology.com" local="3603428142" remote="3631730220" Dst="-1" /><file name="ms-users.php" server="ftp.jackasstheology.com" local="3462941892" remote="3631730220" Dst="-1" /><file name="admin-header.php" server="ftp.jackasstheology.com" local="3623051680" remote="3631730220" Dst="-1" /><file name="load-styles.php" server="ftp.jackasstheology.com" local="3622101802" remote="3631730220" Dst="-1" /><file name="link-add.php" server="ftp.jackasstheology.com" local="3550086990" remote="3631730220" Dst="-1" /><file name="edit-comments.php" server="ftp.jackasstheology.com" local="3603428142" remote="3631730220" Dst="-1" /><file name="moderation.php" server="ftp.jackasstheology.com" local="3462941892" remote="3631730220" Dst="-1" /><file name="ms-options.php" server="ftp.jackasstheology.com" local="3462941892" remote="3631730220" Dst="-1" /><file name="options-head.php" server="ftp.jackasstheology.com" local="3546038492" remote="3631730220" Dst="-1" /><file name="upgrade-functions.php" server="ftp.jackasstheology.com" local="3550682430" remote="3631730220" Dst="-1" /><file name="admin-footer.php" server="ftp.jackasstheology.com" local="3566846322" remote="3631730220" Dst="-1" /><file name="import.php" server="ftp.jackasstheology.com" local="3558486454" remote="3631730220" Dst="-1" /><file name="post.php" server="ftp.jackasstheology.com" local="3629768386" remote="3631730220" Dst="-1" /><file name="edit-form-advanced.php" server="ftp.jackasstheology.com" local="3623675364" remote="3631730220" Dst="-1" /><file name="install.php" server="ftp.jackasstheology.com" local="3587427044" remote="3631730220" Dst="-1" /><file name="index.php" server="ftp.jackasstheology.com" local="3623166280" remote="3631730220" Dst="-1" /><file name="themes.php" server="ftp.jackasstheology.com" local="3603428142" remote="3631730220" Dst="-1" /><file name="link.php" server="ftp.jackasstheology.com" local="3550985490" remote="3631730220" Dst="-1" /><file name="ms-admin.php" server="ftp.jackasstheology.com" local="3462941892" remote="3631730220" Dst="-1" /><file name="install-helper.php" server="ftp.jackasstheology.com" local="3527739866" remote="3631730220" Dst="-1" /><file name="media-upload.php" server="ftp.jackasstheology.com" local="3603428142" remote="3631730220" Dst="-1" /><file name="options-reading.php" server="ftp.jackasstheology.com" local="3587934044" remote="3631730220" Dst="-1" /><file name="options.php" server="ftp.jackasstheology.com" local="3615325706" remote="3631730220" Dst="-1" /><file name="theme-editor.php" server="ftp.jackasstheology.com" local="3594628420" remote="3631730220" Dst="-1" /><file name="admin-functions.php" server="ftp.jackasstheology.com" local="3550682430" remote="3631730280" Dst="-1" /><file name="export.php" server="ftp.jackasstheology.com" local="3558486454" remote="3631730280" Dst="-1" /><file name="options-general.php" server="ftp.jackasstheology.com" local="3599708378" remote="3631730280" Dst="-1" /><file name="ms-edit.php" server="ftp.jackasstheology.com" local="3462941892" remote="3631730280" Dst="-1" /><file name="term.php" server="ftp.jackasstheology.com" local="3603428142" remote="3631730280" Dst="-1" /><file name="nav-menus.php" server="ftp.jackasstheology.com" local="3626483146" remote="3631730280" Dst="-1" /><file name="edit-link-form.php" server="ftp.jackasstheology.com" local="3623675364" remote="3631730280" Dst="-1" /><file name="menu-header.php" server="ftp.jackasstheology.com" local="3587842244" remote="3631730280" Dst="-1" /><file name="plugin-editor.php" server="ftp.jackasstheology.com" local="3591744468" remote="3631730280" Dst="-1" /><file name="update-core.php" server="ftp.jackasstheology.com" local="3590034226" remote="3631730280" Dst="-1" /><file name="edit-form-comment.php" server="ftp.jackasstheology.com" local="3623675364" remote="3631730280" Dst="-1" /><file name="comment.php" server="ftp.jackasstheology.com" local="3558437670" remote="3631730280" Dst="-1" /><file name="plugins.php" server="ftp.jackasstheology.com" local="3623166280" remote="3631730280" Dst="-1" /><file name="ms-delete-site.php" server="ftp.jackasstheology.com" local="3591247730" remote="3631730280" Dst="-1" /><file name="edit-tags.php" server="ftp.jackasstheology.com" local="3603428142" remote="3631730280" Dst="-1" /><file name="async-upload.php" server="ftp.jackasstheology.com" local="3588885348" remote="3631730280" Dst="-1" /><file name="ms-upgrade-network.php" server="ftp.jackasstheology.com" local="3462941892" remote="3631730280" Dst="-1" /><file name="tools.php" server="ftp.jackasstheology.com" local="3608773228" remote="3631730280" Dst="-1" /><file name="options-writing.php" server="ftp.jackasstheology.com" local="3591715912" remote="3631730280" Dst="-1" /><file name="load-scripts.php" server="ftp.jackasstheology.com" local="3624542692" remote="3631730280" Dst="-1" /><file name="media-new.php" server="ftp.jackasstheology.com" local="3558486454" remote="3631730280" Dst="-1" /><file name="custom-header.php" server="ftp.jackasstheology.com" local="3603428142" remote="3631730280" Dst="-1" /><file name="setup-config.php" server="ftp.jackasstheology.com" local="3591214074" remote="3631730280" Dst="-1" /><file name="upgrade.php" server="ftp.jackasstheology.com" local="3532485388" remote="3631730280" Dst="-1" /><file name="privacy.php" server="ftp.jackasstheology.com" local="3614904986" remote="3631730280" Dst="-1" /><file name="press-this.php" server="ftp.jackasstheology.com" local="3603428142" remote="3631730280" Dst="-1" /><file name="users.php" server="ftp.jackasstheology.com" local="3603428142" remote="3631730280" Dst="-1" /><file name="options-discussion.php" server="ftp.jackasstheology.com" local="3615325706" remote="3631730280" Dst="-1" /><file name="menu.php" server="ftp.jackasstheology.com" local="3608856506" remote="3631730280" Dst="-1" /><file name="upload.php" server="ftp.jackasstheology.com" local="3573855524" remote="3631730280" Dst="-1" /><file name="ms-sites.php" server="ftp.jackasstheology.com" local="3462941892" remote="3631730280" Dst="-1" /><file name="ms-themes.php" server="ftp.jackasstheology.com" local="3462941892" remote="3631730280" Dst="-1" /><file name="options-media.php" server="ftp.jackasstheology.com" local="3604459780" remote="3631730280" Dst="-1" /><file name="theme-install.php" server="ftp.jackasstheology.com" local="3598918240" remote="3631730280" Dst="-1" /><file name="customize.php" server="ftp.jackasstheology.com" local="3603428142" remote="3631730280" Dst="-1" /><file name="plugin-install.php" server="ftp.jackasstheology.com" local="3586276368" remote="3631730280" Dst="-1" /><file name="profile.php" server="ftp.jackasstheology.com" local="3462941892" remote="3631730280" Dst="-1" /><file name="edit-tag-form.php" server="ftp.jackasstheology.com" local="3589396786" remote="3631730280" Dst="-1" /><file name="user-new.php" server="ftp.jackasstheology.com" local="3603428142" remote="3631730280" Dst="-1" /><file name="edit.php" server="ftp.jackasstheology.com" local="3625835746" remote="3631730280" Dst="-1" /><file name="link-parse-opml.php" server="ftp.jackasstheology.com" local="3560157932" remote="3631730280" Dst="-1" /><file name="credits.php" server="ftp.jackasstheology.com" local="3625773886" remote="3631730280" Dst="-1" /><file name="network.php" server="ftp.jackasstheology.com" local="3586276368" remote="3631730280" Dst="-1" /><file name="freedoms.php" server="ftp.jackasstheology.com" local="3625783426" remote="3631730280" Dst="-1" /><file name="admin-post.php" server="ftp.jackasstheology.com" local="3539278408" remote="3631730280" Dst="-1" /><file name="admin-ajax.php" server="ftp.jackasstheology.com" local="3623166280" remote="3631730280" Dst="-1" /><file name="admin.php" server="ftp.jackasstheology.com" local="3591759648" remote="3631730280" Dst="-1" /><file name="about.php" server="ftp.jackasstheology.com" local="3629929246" remote="3631730280" Dst="-1" /><file name="media.php" server="ftp.jackasstheology.com" local="3564027040" remote="3631730280" Dst="-1" /><file name="edit-form-blocks.php" server="ftp.jackasstheology.com" local="3629768386" remote="3631730280" Dst="-1" /><file name="my-sites.php" server="ftp.jackasstheology.com" local="3590436166" remote="3631730280" Dst="-1" /><file name="user-edit.php" server="ftp.jackasstheology.com" local="3588729288" remote="3631730280" Dst="-1" /><file name="custom-background.php" server="ftp.jackasstheology.com" local="3583989644" remote="3631730280" Dst="-1" /><file name="link-manager.php" server="ftp.jackasstheology.com" local="3564015526" remote="3631730280" Dst="-1" /></dwsync>